NiukeCeshiGongchengshiQiuzhiJingyanFenxiang20212022Fix1/README.md
NiukeCeshiGongchengshiQiuzhiJingyanFenxiang20212022Fix1/__init__.py
NiukeCeshiGongchengshiQiuzhiJingyanFenxiang20212022Fix1/__main__.py
NiukeCeshiGongchengshiQiuzhiJingyanFenxiang20212022Fix1/file.epub
NiukeCeshiGongchengshiQiuzhiJingyanFenxiang20212022Fix1/index.html
NiukeCeshiGongchengshiQiuzhiJingyanFenxiang20212022Fix1/css/__init__.py
NiukeCeshiGongchengshiQiuzhiJingyanFenxiang20212022Fix1/css/annotations.css
NiukeCeshiGongchengshiQiuzhiJingyanFenxiang20212022Fix1/css/main.css
NiukeCeshiGongchengshiQiuzhiJingyanFenxiang20212022Fix1/css/normalize.css
NiukeCeshiGongchengshiQiuzhiJingyanFenxiang20212022Fix1/css/popup.css
NiukeCeshiGongchengshiQiuzhiJingyanFenxiang20212022Fix1/font/__init__.py
NiukeCeshiGongchengshiQiuzhiJingyanFenxiang20212022Fix1/font/fontello.eot
NiukeCeshiGongchengshiQiuzhiJingyanFenxiang20212022Fix1/font/fontello.svg
NiukeCeshiGongchengshiQiuzhiJingyanFenxiang20212022Fix1/font/fontello.ttf
NiukeCeshiGongchengshiQiuzhiJingyanFenxiang20212022Fix1/font/fontello.woff
NiukeCeshiGongchengshiQiuzhiJingyanFenxiang20212022Fix1/img/__init__.py
NiukeCeshiGongchengshiQiuzhiJingyanFenxiang20212022Fix1/img/annotator-glyph-sprite.png
NiukeCeshiGongchengshiQiuzhiJingyanFenxiang20212022Fix1/img/annotator-icon-sprite.png
NiukeCeshiGongchengshiQiuzhiJingyanFenxiang20212022Fix1/img/apple-touch-icon.png
NiukeCeshiGongchengshiQiuzhiJingyanFenxiang20212022Fix1/img/cancelfullscreen.png
NiukeCeshiGongchengshiQiuzhiJingyanFenxiang20212022Fix1/img/close.png
NiukeCeshiGongchengshiQiuzhiJingyanFenxiang20212022Fix1/img/fullscreen.png
NiukeCeshiGongchengshiQiuzhiJingyanFenxiang20212022Fix1/img/loader.gif
NiukeCeshiGongchengshiQiuzhiJingyanFenxiang20212022Fix1/img/menu-icon.png
NiukeCeshiGongchengshiQiuzhiJingyanFenxiang20212022Fix1/img/save.png
NiukeCeshiGongchengshiQiuzhiJingyanFenxiang20212022Fix1/img/saved.png
NiukeCeshiGongchengshiQiuzhiJingyanFenxiang20212022Fix1/img/settings-s.png
niuke_ceshi_gongchengshi_qiuzhi_jingyan_fenxiang_2021_2022_fix1-2025.3.25.0.dist-info/METADATA
niuke_ceshi_gongchengshi_qiuzhi_jingyan_fenxiang_2021_2022_fix1-2025.3.25.0.dist-info/WHEEL
niuke_ceshi_gongchengshi_qiuzhi_jingyan_fenxiang_2021_2022_fix1-2025.3.25.0.dist-info/entry_points.txt
niuke_ceshi_gongchengshi_qiuzhi_jingyan_fenxiang_2021_2022_fix1-2025.3.25.0.dist-info/top_level.txt
niuke_ceshi_gongchengshi_qiuzhi_jingyan_fenxiang_2021_2022_fix1-2025.3.25.0.dist-info/RECORD
